PiPy_Joywins_sample/__init__.py
PiPy_Joywins_sample/joywins_password_make_sample.py
Joywins-0.0.1.dist-info/METADATA
Joywins-0.0.1.dist-info/WHEEL
Joywins-0.0.1.dist-info/top_level.txt
Joywins-0.0.1.dist-info/RECORD
