Metadata-Version: 2.1
Name: Joywins
Version: 0.0.1
Summary: sample package
Home-page: https://github.com/JoyWins123/
Author: Joywins
Author-email: joywins25@gmail.com
Classifier: Programming Language :: Python :: 3
Classifier: License :: OSI Approved :: MIT License
Classifier: Operating System :: OS Independent
Requires-Python: >=3.6
